datalib/__init__.py
datalib/analysis.py
datalib/data_statistics.py
datalib/enhanced_fever_medicine_recommendation.csv
datalib/filled_data.csv
datalib/filled_fever_medicine_data.csv
datalib/main.py
datalib/manipulation.py
datalib/visualization.py
my_datalib_sirine-2.0.0.dist-info/LICENSE
my_datalib_sirine-2.0.0.dist-info/METADATA
my_datalib_sirine-2.0.0.dist-info/WHEEL
my_datalib_sirine-2.0.0.dist-info/RECORD
