Metadata-Version: 2.1
Name: my-datalib-sirine
Version: 2.0.0
Summary: 
Author: sirine-de
Author-email: sirine.pfe22@gmail.com
Requires-Python: >=3.10,<4.0
Classifier: Programming Language :: Python :: 3
Classifier: Programming Language :: Python :: 3.10
Classifier: Programming Language :: Python :: 3.11
Classifier: Programming Language :: Python :: 3.12
Classifier: Programming Language :: Python :: 3.13
Requires-Dist: matplotlib (>=3.6,<4.0)
Requires-Dist: numpy (>=1.23,<2.0)
Requires-Dist: pandas (>=1.5,<2.0)
Requires-Dist: scikit-learn (>=1.2,<2.0)
Requires-Dist: scipy (>=1.14.1,<2.0.0)
Requires-Dist: seaborn (>=0.13.2,<0.14.0)
